Workbook

Sheet Dashboard
A1: Meridian Retail Group — Financial Health Dashboard
A2: Liquidity, profitability, leverage & efficiency at a glance — FY2020 to FY2024
A4: LIQUIDITY | C4: PROFITABILITY | E4: PROFITABILITY | G4: LEVERAGE | I4: LEVERAGE | K4: EFFICIENCY
A5: Current Ratio | C5: Net Profit Margin | E5: Return on Equity (ROE) | G5: Debt-to-Equity | I5: Interest Coverage | K5: Asset Turnover
A6: =INDEX('Ratio Calculations'!$G$5:$G$5,1) -> #N/A | C6: =INDEX('Ratio Calculations'!$G$10:$G$10,1) -> #N/A | E6: =INDEX('Ratio Calculations'!$G$12:$G$12,1) -> #N/A | G6: =INDEX('Ratio Calculations'!$G$13:$G$13,1) -> #N/A | I6: =INDEX('Ratio Calculations'!$G$15:$G$15,1) -> 0 | K6: =INDEX('Ratio Calculations'!$G$16:$G$16,1) -> #N/A
A7: =INDEX('Ratio Calculations'!$J$5:$J$5,1)&" · FY2024" -> #N/A | C7: =INDEX('Ratio Calculations'!$J$10:$J$10,1)&" · FY2024" -> #N/A | E7: =INDEX('Ratio Calculations'!$J$12:$J$12,1)&" · FY2024" -> #N/A | G7: =INDEX('Ratio Calculations'!$J$13:$J$13,1)&" · FY2024" -> #N/A | I7: =INDEX('Ratio Calculations'!$J$15:$J$15,1)&" · FY2024" -> Weak · FY2024 | K7: =INDEX('Ratio Calculations'!$J$16:$J$16,1)&" · FY2024" -> #N/A

Sheet Ratio Calculations
A1: Financial Ratio Calculations, FY2020–FY2024
A2: Every ratio is pulled from the Raw Data sheet with a two-way INDEX-MATCH (row = line item, column = year). Benchmarks are pulled with VLOOKUP; the Rating column uses a nested IF against those benchmarks.
A4: Category | B4: Ratio | C4: 2020 | D4: 2021 | E4: 2022 | F4: 2023 | G4: 2024 | H4: Direction | I4: Strong ≥/≤ | J4: 2024 Rating
A5: Liquidity | B5: Current Ratio | C5: =(INDEX('Raw Data'!$B$5:$F$40,MATCH("Total Current Assets",'Raw Data'!$A$5:$A$40,0),MATCH(C$4,'Raw Data'!$B$4:$F$4,0)))/(INDEX('Raw Data'!$B$5:$F$40,MATCH("Total Current Liabilities",'Raw Data'!$A$5:$A$40,0),MATCH(C$4,'Raw Data'!$B$4:$F$4,0))) -> #N/A | D5: =(INDEX('Raw Data'!$B$5:$F$40,MATCH("Total Current Assets",'Raw Data'!$A$5:$A$40,0),MATCH(D$4,'Raw Data'!$B$4:$F$4,0)))/(INDEX('Raw Data'!$B$5:$F$40,MATCH("Total Current Liabilities",'Raw Data'!$A$5:$A$40,0),MATCH(D$4,'Raw Data'!$B$4:$F$4,0))) -> #N/A | E5: =(INDEX('Raw Data'!$B$5:$F$40,MATCH("Total Current Assets",'Raw Data'!$A$5:$A$40,0),MATCH(E$4,'Raw Data'!$B$4:$F$4,0)))/(INDEX('Raw Data'!$B$5:$F$40,MATCH("Total Current Liabilities",'Raw Data'!$A$5:$A$40,0),MATCH(E$4,'Raw Data'!$B$4:$F$4,0))) -> #N/A | F5: =(INDEX('Raw Data'!$B$5:$F$40,MATCH("Total Current Assets",'Raw Data'!$A$5:$A$40,0),MATCH(F$4,'Raw Data'!$B$4:$F$4,0)))/(INDEX('Raw Data'!$B$5:$F$40,MATCH("Total Current Liabilities",'Raw Data'!$A$5:$A$40,0),MATCH(F$4,'Raw Data'!$B$4:$F$4,0))) -> #N/A | G5: =(INDEX('Raw Data'!$B$5:$F$40,MATCH("Total Current Assets",'Raw Data'!$A$5:$A$40,0),MATCH(G$4,'Raw Data'!$B$4:$F$4,0)))/(INDEX('Raw Data'!$B$5:$F$40,MATCH("Total Current Liabilities",'Raw Data'!$A$5:$A$40,0),MATCH(G$4,'Raw Data'!$B$4:$F$4,0))) -> #N/A | H5: =VLOOKUP($B5,Benchmarks!$A$5:$E$18,2,FALSE()) -> Higher | I5: =VLOOKUP($B5,Benchmarks!$A$5:$E$18,3,FALSE()) -> 2 | J5: =IF(H5="Higher",IF(G5>=I5,"Strong",IF(G5>=VLOOKUP($B5,Benchmarks!$A$5:$E$18,4,FALSE()),"Moderate","Weak")),IF(G5<=I5,"Strong",IF(G5<=VLOOKUP($B5,Benchmarks!$A$5:$E$18,4,FALSE()),"Moderate","Weak"))) -> #N/A
A6: Liquidity | B6: Quick Ratio | C6: =(INDEX('Raw Data'!$B$5:$F$40,MATCH("Total Current Assets",'Raw Data'!$A$5:$A$40,0),MATCH(C$4,'Raw Data'!$B$4:$F$4,0))-INDEX('Raw Data'!$B$5:$F$40,MATCH("Inventory",'Raw Data'!$A$5:$A$40,0),MATCH(C$4,'Raw Data'!$B$4:$F$4,0)))/(INDEX('Raw Data'!$B$5:$F$40,MATCH("Total Current Liabilities",'Raw Data'!$A$5:$A$40,0),MATCH(C$4,'Raw Data'!$B$4:$F$4,0))) -> #N/A | D6: =(INDEX('Raw Data'!$B$5:$F$40,MATCH("Total Current Assets",'Raw Data'!$A$5:$A$40,0),MATCH(D$4,'Raw Data'!$B$4:$F$4,0))-INDEX('Raw Data'!$B$5:$F$40,MATCH("Inventory",'Raw Data'!$A$5:$A$40,0),MATCH(D$4,'Raw Data'!$B$4:$F$4,0)))/(INDEX('Raw Data'!$B$5:$F$40,MATCH("Total Current Liabilities",'Raw Data'!$A$5:$A$40,0),MATCH(D$4,'Raw Data'!$B$4:$F$4,0))) -> #N/A | E6: =(INDEX('Raw Data'!$B$5:$F$40,MATCH("Total Current Assets",'Raw Data'!$A$5:$A$40,0),MATCH(E$4,'Raw Data'!$B$4:$F$4,0))-INDEX('Raw Data'!$B$5:$F$40,MATCH("Inventory",'Raw Data'!$A$5:$A$40,0),MATCH(E$4,'Raw Data'!$B$4:$F$4,0)))/(INDEX('Raw Data'!$B$5:$F$40,MATCH("Total Current Liabilities",'Raw Data'!$A$5:$A$40,0),MATCH(E$4,'Raw Data'!$B$4:$F$4,0))) -> #N/A | F6: =(INDEX('Raw Data'!$B$5:$F$40,MATCH("Total Current Assets",'Raw Data'!$A$5:$A$40,0),MATCH(F$4,'Raw Data'!$B$4:$F$4,0))-INDEX('Raw Data'!$B$5:$F$40,MATCH("Inventory",'Raw Data'!$A$5:$A$40,0),MATCH(F$4,'Raw Data'!$B$4:$F$4,0)))/(INDEX('Raw Data'!$B$5:$F$40,MATCH("Total Current Liabilities",'Raw Data'!$A$5:$A$40,0),MATCH(F$4,'Raw Data'!$B$4:$F$4,0))) -> #N/A | G6: =(INDEX('Raw Data'!$B$5:$F$40,MATCH("Total Current Assets",'Raw Data'!$A$5:$A$40,0),MATCH(G$4,'Raw Data'!$B$4:$F$4,0))-INDEX('Raw Data'!$B$5:$F$40,MATCH("Inventory",'Raw Data'!$A$5:$A$40,0),MATCH(G$4,'Raw Data'!$B$4:$F$4,0)))/(INDEX('Raw Data'!$B$5:$F$40,MATCH("Total Current Liabilities",'Raw Data'!$A$5:$A$40,0),MATCH(G$4,'Raw Data'!$B$4:$F$4,0))) -> #N/A | H6: =VLOOKUP($B6,Benchmarks!$A$5:$E$18,2,FALSE()) -> Higher | I6: =VLOOKUP($B6,Benchmarks!$A$5:$E$18,3,FALSE()) -> 1 | J6: =IF(H6="Higher",IF(G6>=I6,"Strong",IF(G6>=VLOOKUP($B6,Benchmarks!$A$5:$E$18,4,FALSE()),"Moderate","Weak")),IF(G6<=I6,"Strong",IF(G6<=VLOOKUP($B6,Benchmarks!$A$5:$E$18,4,FALSE()),"Moderate","Weak"))) -> #N/A
A7: Liquidity | B7: Cash Ratio | C7: =(INDEX('Raw Data'!$B$5:$F$40,MATCH("Cash & Equivalents",'Raw Data'!$A$5:$A$40,0),MATCH(C$4,'Raw Data'!$B$4:$F$4,0)))/(INDEX('Raw Data'!$B$5:$F$40,MATCH("Total Current Liabilities",'Raw Data'!$A$5:$A$40,0),MATCH(C$4,'Raw Data'!$B$4:$F$4,0))) -> #N/A | D7: =(INDEX('Raw Data'!$B$5:$F$40,MATCH("Cash & Equivalents",'Raw Data'!$A$5:$A$40,0),MATCH(D$4,'Raw Data'!$B$4:$F$4,0)))/(INDEX('Raw Data'!$B$5:$F$40,MATCH("Total Current Liabilities",'Raw Data'!$A$5:$A$40,0),MATCH(D$4,'Raw Data'!$B$4:$F$4,0))) -> #N/A | E7: =(INDEX('Raw Data'!$B$5:$F$40,MATCH("Cash & Equivalents",'Raw Data'!$A$5:$A$40,0),MATCH(E$4,'Raw Data'!$B$4:$F$4,0)))/(INDEX('Raw Data'!$B$5:$F$40,MATCH("Total Current Liabilities",'Raw Data'!$A$5:$A$40,0),MATCH(E$4,'Raw Data'!$B$4:$F$4,0))) -> #N/A | F7: =(INDEX('Raw Data'!$B$5:$F$40,MATCH("Cash & Equivalents",'Raw Data'!$A$5:$A$40,0),MATCH(F$4,'Raw Data'!$B$4:$F$4,0)))/(INDEX('Raw Data'!$B$5:$F$40,MATCH("Total Current Liabilities",'Raw Data'!$A$5:$A$40,0),MATCH(F$4,'Raw Data'!$B$4:$F$4,0))) -> #N/A | G7: =(INDEX('Raw Data'!$B$5:$F$40,MATCH("Cash & Equivalents",'Raw Data'!$A$5:$A$40,0),MATCH(G$4,'Raw Data'!$B$4:$F$4,0)))/(INDEX('Raw Data'!$B$5:$F$40,MATCH("Total Current Liabilities",'Raw Data'!$A$5:$A$40,0),MATCH(G$4,'Raw Data'!$B$4:$F$4,0))) -> #N/A | H7: =VLOOKUP($B7,Benchmarks!$A$5:$E$18,2,FALSE()) -> Higher | I7: =VLOOKUP($B7,Benchmarks!$A$5:$E$18,3,FALSE()) -> 0.5 | J7: =IF(H7="Higher",IF(G7>=I7,"Strong",IF(G7>=VLOOKUP($B7,Benchmarks!$A$5:$E$18,4,FALSE()),"Moderate","Weak")),IF(G7<=I7,"Strong",IF(G7<=VLOOKUP($B7,Benchmarks!$A$5:$E$18,4,FALSE()),"Moderate","Weak"))) -> #N/A
A8: Profitability | B8: Gross Margin | C8: =(INDEX('Raw Data'!$B$5:$F$40,MATCH("Gross Profit",'Raw Data'!$A$5:$A$40,0),MATCH(C$4,'Raw Data'!$B$4:$F$4,0)))/(INDEX('Raw Data'!$B$5:$F$40,MATCH("Revenue",'Raw Data'!$A$5:$A$40,0),MATCH(C$4,'Raw Data'!$B$4:$F$4,0))) -> #N/A | D8: =(INDEX('Raw Data'!$B$5:$F$40,MATCH("Gross Profit",'Raw Data'!$A$5:$A$40,0),MATCH(D$4,'Raw Data'!$B$4:$F$4,0)))/(INDEX('Raw Data'!$B$5:$F$40,MATCH("Revenue",'Raw Data'!$A$5:$A$40,0),MATCH(D$4,'Raw Data'!$B$4:$F$4,0))) -> #N/A | E8: =(INDEX('Raw Data'!$B$5:$F$40,MATCH("Gross Profit",'Raw Data'!$A$5:$A$40,0),MATCH(E$4,'Raw Data'!$B$4:$F$4,0)))/(INDEX('Raw Data'!$B$5:$F$40,MATCH("Revenue",'Raw Data'!$A$5:$A$40,0),MATCH(E$4,'Raw Data'!$B$4:$F$4,0))) -> #N/A | F8: =(INDEX('Raw Data'!$B$5:$F$40,MATCH("Gross Profit",'Raw Data'!$A$5:$A$40,0),MATCH(F$4,'Raw Data'!$B$4:$F$4,0)))/(INDEX('Raw Data'!$B$5:$F$40,MATCH("Revenue",'Raw Data'!$A$5:$A$40,0),MATCH(F$4,'Raw Data'!$B$4:$F$4,0))) -> #N/A | G8: =(INDEX('Raw Data'!$B$5:$F$40,MATCH("Gross Profit",'Raw Data'!$A$5:$A$40,0),MATCH(G$4,'Raw Data'!$B$4:$F$4,0)))/(INDEX('Raw Data'!$B$5:$F$40,MATCH("Revenue",'Raw Data'!$A$5:$A$40,0),MATCH(G$4,'Raw Data'!$B$4:$F$4,0))) -> #N/A | H8: =VLOOKUP($B8,Benchmarks!$A$5:$E$18,2,FALSE()) -> Higher | I8: =VLOOKUP($B8,Benchmarks!$A$5:$E$18,3,FALSE()) -> 0.4 | J8: =IF(H8="Higher",IF(G8>=I8,"Strong",IF(G8>=VLOOKUP($B8,Benchmarks!$A$5:$E$18,4,FALSE()),"Moderate","Weak")),IF(G8<=I8,"Strong",IF(G8<=VLOOKUP($B8,Benchmarks!$A$5:$E$18,4,FALSE()),"Moderate","Weak"))) -> #N/A
A9: Profitability | B9: Operating Margin | C9: =(INDEX('Raw Data'!$B$5:$F$40,MATCH("Operating Income (EBIT)",'Raw Data'!$A$5:$A$40,0),MATCH(C$4,'Raw Data'!$B$4:$F$4,0)))/(INDEX('Raw Data'!$B$5:$F$40,MATCH("Revenue",'Raw Data'!$A$5:$A$40,0),MATCH(C$4,'Raw Data'!$B$4:$F$4,0))) -> #N/A | D9: =(INDEX('Raw Data'!$B$5:$F$40,MATCH("Operating Income (EBIT)",'Raw Data'!$A$5:$A$40,0),MATCH(D$4,'Raw Data'!$B$4:$F$4,0)))/(INDEX('Raw Data'!$B$5:$F$40,MATCH("Revenue",'Raw Data'!$A$5:$A$40,0),MATCH(D$4,'Raw Data'!$B$4:$F$4,0))) -> #N/A | E9: =(INDEX('Raw Data'!$B$5:$F$40,MATCH("Operating Income (EBIT)",'Raw Data'!$A$5:$A$40,0),MATCH(E$4,'Raw Data'!$B$4:$F$4,0)))/(INDEX('Raw Data'!$B$5:$F$40,MATCH("Revenue",'Raw Data'!$A$5:$A$40,0),MATCH(E$4,'Raw Data'!$B$4:$F$4,0))) -> #N/A | F9: =(INDEX('Raw Data'!$B$5:$F$40,MATCH("Operating Income (EBIT)",'Raw Data'!$A$5:$A$40,0),MATCH(F$4,'Raw Data'!$B$4:$F$4,0)))/(INDEX('Raw Data'!$B$5:$F$40,MATCH("Revenue",'Raw Data'!$A$5:$A$40,0),MATCH(F$4,'Raw Data'!$B$4:$F$4,0))) -> #N/A | G9: =(INDEX('Raw Data'!$B$5:$F$40,MATCH("Operating Income (EBIT)",'Raw Data'!$A$5:$A$40,0),MATCH(G$4,'Raw Data'!$B$4:$F$4,0)))/(INDEX('Raw Data'!$B$5:$F$40,MATCH("Revenue",'Raw Data'!$A$5:$A$40,0),MATCH(G$4,'Raw Data'!$B$4:$F$4,0))) -> #N/A | H9: =VLOOKUP($B9,Benchmarks!$A$5:$E$18,2,FALSE()) -> Higher | I9: =VLOOKUP($B9,Benchmarks!$A$5:$E$18,3,FALSE()) -> 0.15 | J9: =IF(H9="Higher",IF(G9>=I9,"Strong",IF(G9>=VLOOKUP($B9,Benchmarks!$A$5:$E$18,4,FALSE()),"Moderate","Weak")),IF(G9<=I9,"Strong",IF(G9<=VLOOKUP($B9,Benchmarks!$A$5:$E$18,4,FALSE()),"Moderate","Weak"))) -> #N/A
A10: Profitability | B10: Net Profit Margin | C10: =(INDEX('Raw Data'!$B$5:$F$40,MATCH("Net Income",'Raw Data'!$A$5:$A$40,0),MATCH(C$4,'Raw Data'!$B$4:$F$4,0)))/(INDEX('Raw Data'!$B$5:$F$40,MATCH("Revenue",'Raw Data'!$A$5:$A$40,0),MATCH(C$4,'Raw Data'!$B$4:$F$4,0))) -> #N/A | D10: =(INDEX('Raw Data'!$B$5:$F$40,MATCH("Net Income",'Raw Data'!$A$5:$A$40,0),MATCH(D$4,'Raw Data'!$B$4:$F$4,0)))/(INDEX('Raw Data'!$B$5:$F$40,MATCH("Revenue",'Raw Data'!$A$5:$A$40,0),MATCH(D$4,'Raw Data'!$B$4:$F$4,0))) -> #N/A | E10: =(INDEX('Raw Data'!$B$5:$F$40,MATCH("Net Income",'Raw Data'!$A$5:$A$40,0),MATCH(E$4,'Raw Data'!$B$4:$F$4,0)))/(INDEX('Raw Data'!$B$5:$F$40,MATCH("Revenue",'Raw Data'!$A$5:$A$40,0),MATCH(E$4,'Raw Data'!$B$4:$F$4,0))) -> #N/A | F10: =(INDEX('Raw Data'!$B$5:$F$40,MATCH("Net Income",'Raw Data'!$A$5:$A$40,0),MATCH(F$4,'Raw Data'!$B$4:$F$4,0)))/(INDEX('Raw Data'!$B$5:$F$40,MATCH("Revenue",'Raw Data'!$A$5:$A$40,0),MATCH(F$4,'Raw Data'!$B$4:$F$4,0))) -> #N/A | G10: =(INDEX('Raw Data'!$B$5:$F$40,MATCH("Net Income",'Raw Data'!$A$5:$A$40,0),MATCH(G$4,'Raw Data'!$B$4:$F$4,0)))/(INDEX('Raw Data'!$B$5:$F$40,MATCH("Revenue",'Raw Data'!$A$5:$A$40,0),MATCH(G$4,'Raw Data'!$B$4:$F$4,0))) -> #N/A | H10: =VLOOKUP($B10,Benchmarks!$A$5:$E$18,2,FALSE()) -> Higher | I10: =VLOOKUP($B10,Benchmarks!$A$5:$E$18,3,FALSE()) -> 0.1 | J10: =IF(H10="Higher",IF(G10>=I10,"Strong",IF(G10>=VLOOKUP($B10,Benchmarks!$A$5:$E$18,4,FALSE()),"Moderate","Weak")),IF(G10<=I10,"Strong",IF(G10<=VLOOKUP($B10,Benchmarks!$A$5:$E$18,4,FALSE()),"Moderate","Weak"))) -> #N/A
A11: Profitability | B11: Return on Assets (ROA) | C11: =(INDEX('Raw Data'!$B$5:$F$40,MATCH("Net Income",'Raw Data'!$A$5:$A$40,0),MATCH(C$4,'Raw Data'!$B$4:$F$4,0)))/(INDEX('Raw Data'!$B$5:$F$40,MATCH("Total Assets",'Raw Data'!$A$5:$A$40,0),MATCH(C$4,'Raw Data'!$B$4:$F$4,0))) -> #N/A | D11: =(INDEX('Raw Data'!$B$5:$F$40,MATCH("Net Income",'Raw Data'!$A$5:$A$40,0),MATCH(D$4,'Raw Data'!$B$4:$F$4,0)))/(INDEX('Raw Data'!$B$5:$F$40,MATCH("Total Assets",'Raw Data'!$A$5:$A$40,0),MATCH(D$4,'Raw Data'!$B$4:$F$4,0))) -> #N/A | E11: =(INDEX('Raw Data'!$B$5:$F$40,MATCH("Net Income",'Raw Data'!$A$5:$A$40,0),MATCH(E$4,'Raw Data'!$B$4:$F$4,0)))/(INDEX('Raw Data'!$B$5:$F$40,MATCH("Total Assets",'Raw Data'!$A$5:$A$40,0),MATCH(E$4,'Raw Data'!$B$4:$F$4,0))) -> #N/A | F11: =(INDEX('Raw Data'!$B$5:$F$40,MATCH("Net Income",'Raw Data'!$A$5:$A$40,0),MATCH(F$4,'Raw Data'!$B$4:$F$4,0)))/(INDEX('Raw Data'!$B$5:$F$40,MATCH("Total Assets",'Raw Data'!$A$5:$A$40,0),MATCH(F$4,'Raw Data'!$B$4:$F$4,0))) -> #N/A | G11: =(INDEX('Raw Data'!$B$5:$F$40,MATCH("Net Income",'Raw Data'!$A$5:$A$40,0),MATCH(G$4,'Raw Data'!$B$4:$F$4,0)))/(INDEX('Raw Data'!$B$5:$F$40,MATCH("Total Assets",'Raw Data'!$A$5:$A$40,0),MATCH(G$4,'Raw Data'!$B$4:$F$4,0))) -> #N/A | H11: =VLOOKUP($B11,Benchmarks!$A$5:$E$18,2,FALSE()) -> Higher | I11: =VLOOKUP($B11,Benchmarks!$A$5:$E$18,3,FALSE()) -> 0.08 | J11: =IF(H11="Higher",IF(G11>=I11,"Strong",IF(G11>=VLOOKUP($B11,Benchmarks!$A$5:$E$18,4,FALSE()),"Moderate","Weak")),IF(G11<=I11,"Strong",IF(G11<=VLOOKUP($B11,Benchmarks!$A$5:$E$18,4,FALSE()),"Moderate","Weak"))) -> #N/A
A12: Profitability | B12: Return on Equity (ROE) | C12: =(INDEX('Raw Data'!$B$5:$F$40,MATCH("Net Income",'Raw Data'!$A$5:$A$40,0),MATCH(C$4,'Raw Data'!$B$4:$F$4,0)))/(INDEX('Raw Data'!$B$5:$F$40,MATCH("Total Shareholders' Equity",'Raw Data'!$A$5:$A$40,0),MATCH(C$4,'Raw Data'!$B$4:$F$4,0))) -> #N/A | D12: =(INDEX('Raw Data'!$B$5:$F$40,MATCH("Net Income",'Raw Data'!$A$5:$A$40,0),MATCH(D$4,'Raw Data'!$B$4:$F$4,0)))/(INDEX('Raw Data'!$B$5:$F$40,MATCH("Total Shareholders' Equity",'Raw Data'!$A$5:$A$40,0),MATCH(D$4,'Raw Data'!$B$4:$F$4,0))) -> #N/A | E12: =(INDEX('Raw Data'!$B$5:$F$40,MATCH("Net Income",'Raw Data'!$A$5:$A$40,0),MATCH(E$4,'Raw Data'!$B$4:$F$4,0)))/(INDEX('Raw Data'!$B$5:$F$40,MATCH("Total Shareholders' Equity",'Raw Data'!$A$5:$A$40,0),MATCH(E$4,'Raw Data'!$B$4:$F$4,0))) -> #N/A | F12: =(INDEX('Raw Data'!$B$5:$F$40,MATCH("Net Income",'Raw Data'!$A$5:$A$40,0),MATCH(F$4,'Raw Data'!$B$4:$F$4,0)))/(INDEX('Raw Data'!$B$5:$F$40,MATCH("Total Shareholders' Equity",'Raw Data'!$A$5:$A$40,0),MATCH(F$4,'Raw Data'!$B$4:$F$4,0))) -> #N/A | G12: =(INDEX('Raw Data'!$B$5:$F$40,MATCH("Net Income",'Raw Data'!$A$5:$A$40,0),MATCH(G$4,'Raw Data'!$B$4:$F$4,0)))/(INDEX('Raw Data'!$B$5:$F$40,MATCH("Total Shareholders' Equity",'Raw Data'!$A$5:$A$40,0),MATCH(G$4,'Raw Data'!$B$4:$F$4,0))) -> #N/A | H12: =VLOOKUP($B12,Benchmarks!$A$5:$E$18,2,FALSE()) -> Higher | I12: =VLOOKUP($B12,Benchmarks!$A$5:$E$18,3,FALSE()) -> 0.15 | J12: =IF(H12="Higher",IF(G12>=I12,"Strong",IF(G12>=VLOOKUP($B12,Benchmarks!$A$5:$E$18,4,FALSE()),"Moderate","Weak")),IF(G12<=I12,"Strong",IF(G12<=VLOOKUP($B12,Benchmarks!$A$5:$E$18,4,FALSE()),"Moderate","Weak"))) -> #N/A
A13: Leverage | B13: Debt-to-Equity | C13: =(INDEX('Raw Data'!$B$5:$F$40,MATCH("Total Liabilities",'Raw Data'!$A$5:$A$40,0),MATCH(C$4,'Raw Data'!$B$4:$F$4,0)))/(INDEX('Raw Data'!$B$5:$F$40,MATCH("Total Shareholders' Equity",'Raw Data'!$A$5:$A$40,0),MATCH(C$4,'Raw Data'!$B$4:$F$4,0))) -> #N/A | D13: =(INDEX('Raw Data'!$B$5:$F$40,MATCH("Total Liabilities",'Raw Data'!$A$5:$A$40,0),MATCH(D$4,'Raw Data'!$B$4:$F$4,0)))/(INDEX('Raw Data'!$B$5:$F$40,MATCH("Total Shareholders' Equity",'Raw Data'!$A$5:$A$40,0),MATCH(D$4,'Raw Data'!$B$4:$F$4,0))) -> #N/A | E13: =(INDEX('Raw Data'!$B$5:$F$40,MATCH("Total Liabilities",'Raw Data'!$A$5:$A$40,0),MATCH(E$4,'Raw Data'!$B$4:$F$4,0)))/(INDEX('Raw Data'!$B$5:$F$40,MATCH("Total Shareholders' Equity",'Raw Data'!$A$5:$A$40,0),MATCH(E$4,'Raw Data'!$B$4:$F$4,0))) -> #N/A | F13: =(INDEX('Raw Data'!$B$5:$F$40,MATCH("Total Liabilities",'Raw Data'!$A$5:$A$40,0),MATCH(F$4,'Raw Data'!$B$4:$F$4,0)))/(INDEX('Raw Data'!$B$5:$F$40,MATCH("Total Shareholders' Equity",'Raw Data'!$A$5:$A$40,0),MATCH(F$4,'Raw Data'!$B$4:$F$4,0))) -> #N/A | G13: =(INDEX('Raw Data'!$B$5:$F$40,MATCH("Total Liabilities",'Raw Data'!$A$5:$A$40,0),MATCH(G$4,'Raw Data'!$B$4:$F$4,0)))/(INDEX('Raw Data'!$B$5:$F$40,MATCH("Total Shareholders' Equity",'Raw Data'!$A$5:$A$40,0),MATCH(G$4,'Raw Data'!$B$4:$F$4,0))) -> #N/A | H13: =VLOOKUP($B13,Benchmarks!$A$5:$E$18,2,FALSE()) -> Lower | I13: =VLOOKUP($B13,Benchmarks!$A$5:$E$18,3,FALSE()) -> 1 | J13: =IF(H13="Higher",IF(G13>=I13,"Strong",IF(G13>=VLOOKUP($B13,Benchmarks!$A$5:$E$18,4,FALSE()),"Moderate","Weak")),IF(G13<=I13,"Strong",IF(G13<=VLOOKUP($B13,Benchmarks!$A$5:$E$18,4,FALSE()),"Moderate","Weak"))) -> #N/A
A14: Leverage | B14: Debt-to-Assets | C14: =(INDEX('Raw Data'!$B$5:$F$40,MATCH("Total Liabilities",'Raw Data'!$A$5:$A$40,0),MATCH(C$4,'Raw Data'!$B$4:$F$4,0)))/(INDEX('Raw Data'!$B$5:$F$40,MATCH("Total Assets",'Raw Data'!$A$5:$A$40,0),MATCH(C$4,'Raw Data'!$B$4:$F$4,0))) -> #N/A | D14: =(INDEX('Raw Data'!$B$5:$F$40,MATCH("Total Liabilities",'Raw Data'!$A$5:$A$40,0),MATCH(D$4,'Raw Data'!$B$4:$F$4,0)))/(INDEX('Raw Data'!$B$5:$F$40,MATCH("Total Assets",'Raw Data'!$A$5:$A$40,0),MATCH(D$4,'Raw Data'!$B$4:$F$4,0))) -> #N/A | E14: =(INDEX('Raw Data'!$B$5:$F$40,MATCH("Total Liabilities",'Raw Data'!$A$5:$A$40,0),MATCH(E$4,'Raw Data'!$B$4:$F$4,0)))/(INDEX('Raw Data'!$B$5:$F$40,MATCH("Total Assets",'Raw Data'!$A$5:$A$40,0),MATCH(E$4,'Raw Data'!$B$4:$F$4,0))) -> #N/A | F14: =(INDEX('Raw Data'!$B$5:$F$40,MATCH("Total Liabilities",'Raw Data'!$A$5:$A$40,0),MATCH(F$4,'Raw Data'!$B$4:$F$4,0)))/(INDEX('Raw Data'!$B$5:$F$40,MATCH("Total Assets",'Raw Data'!$A$5:$A$40,0),MATCH(F$4,'Raw Data'!$B$4:$F$4,0))) -> #N/A | G14: =(INDEX('Raw Data'!$B$5:$F$40,MATCH("Total Liabilities",'Raw Data'!$A$5:$A$40,0),MATCH(G$4,'Raw Data'!$B$4:$F$4,0)))/(INDEX('Raw Data'!$B$5:$F$40,MATCH("Total Assets",'Raw Data'!$A$5:$A$40,0),MATCH(G$4,'Raw Data'!$B$4:$F$4,0))) -> #N/A | H14: =VLOOKUP($B14,Benchmarks!$A$5:$E$18,2,FALSE()) -> Lower | I14: =VLOOKUP($B14,Benchmarks!$A$5:$E$18,3,FALSE()) -> 0.45 | J14: =IF(H14="Higher",IF(G14>=I14,"Strong",IF(G14>=VLOOKUP($B14,Benchmarks!$A$5:$E$18,4,FALSE()),"Moderate","Weak")),IF(G14<=I14,"Strong",IF(G14<=VLOOKUP($B14,Benchmarks!$A$5:$E$18,4,FALSE()),"Moderate","Weak"))) -> #N/A
A15: Leverage | B15: Interest Coverage | C15: =IFERROR((INDEX('Raw Data'!$B$5:$F$40,MATCH("Operating Income (EBIT)",'Raw Data'!$A$5:$A$40,0),MATCH(C$4,'Raw Data'!$B$4:$F$4,0)))/(INDEX('Raw Data'!$B$5:$F$40,MATCH("Interest Expense",'Raw Data'!$A$5:$A$40,0),MATCH(C$4,'Raw Data'!$B$4:$F$4,0))),0) -> 0 | D15: =IFERROR((INDEX('Raw Data'!$B$5:$F$40,MATCH("Operating Income (EBIT)",'Raw Data'!$A$5:$A$40,0),MATCH(D$4,'Raw Data'!$B$4:$F$4,0)))/(INDEX('Raw Data'!$B$5:$F$40,MATCH("Interest Expense",'Raw Data'!$A$5:$A$40,0),MATCH(D$4,'Raw Data'!$B$4:$F$4,0))),0) -> 0 | E15: =IFERROR((INDEX('Raw Data'!$B$5:$F$40,MATCH("Operating Income (EBIT)",'Raw Data'!$A$5:$A$40,0),MATCH(E$4,'Raw Data'!$B$4:$F$4,0)))/(INDEX('Raw Data'!$B$5:$F$40,MATCH("Interest Expense",'Raw Data'!$A$5:$A$40,0),MATCH(E$4,'Raw Data'!$B$4:$F$4,0))),0) -> 0 | F15: =IFERROR((INDEX('Raw Data'!$B$5:$F$40,MATCH("Operating Income (EBIT)",'Raw Data'!$A$5:$A$40,0),MATCH(F$4,'Raw Data'!$B$4:$F$4,0)))/(INDEX('Raw Data'!$B$5:$F$40,MATCH("Interest Expense",'Raw Data'!$A$5:$A$40,0),MATCH(F$4,'Raw Data'!$B$4:$F$4,0))),0) -> 0 | G15: =IFERROR((INDEX('Raw Data'!$B$5:$F$40,MATCH("Operating Income (EBIT)",'Raw Data'!$A$5:$A$40,0),MATCH(G$4,'Raw Data'!$B$4:$F$4,0)))/(INDEX('Raw Data'!$B$5:$F$40,MATCH("Interest Expense",'Raw Data'!$A$5:$A$40,0),MATCH(G$4,'Raw Data'!$B$4:$F$4,0))),0) -> 0 | H15: =VLOOKUP($B15,Benchmarks!$A$5:$E$18,2,FALSE()) -> Higher | I15: =VLOOKUP($B15,Benchmarks!$A$5:$E$18,3,FALSE()) -> 6 | J15: =IF(H15="Higher",IF(G15>=I15,"Strong",IF(G15>=VLOOKUP($B15,Benchmarks!$A$5:$E$18,4,FALSE()),"Moderate","Weak")),IF(G15<=I15,"Strong",IF(G15<=VLOOKUP($B15,Benchmarks!$A$5:$E$18,4,FALSE()),"Moderate","Weak"))) -> Weak
A16: Efficiency | B16: Asset Turnover | C16: =(INDEX('Raw Data'!$B$5:$F$40,MATCH("Revenue",'Raw Data'!$A$5:$A$40,0),MATCH(C$4,'Raw Data'!$B$4:$F$4,0)))/(INDEX('Raw Data'!$B$5:$F$40,MATCH("Total Assets",'Raw Data'!$A$5:$A$40,0),MATCH(C$4,'Raw Data'!$B$4:$F$4,0))) -> #N/A | D16: =(INDEX('Raw Data'!$B$5:$F$40,MATCH("Revenue",'Raw Data'!$A$5:$A$40,0),MATCH(D$4,'Raw Data'!$B$4:$F$4,0)))/(INDEX('Raw Data'!$B$5:$F$40,MATCH("Total Assets",'Raw Data'!$A$5:$A$40,0),MATCH(D$4,'Raw Data'!$B$4:$F$4,0))) -> #N/A | E16: =(INDEX('Raw Data'!$B$5:$F$40,MATCH("Revenue",'Raw Data'!$A$5:$A$40,0),MATCH(E$4,'Raw Data'!$B$4:$F$4,0)))/(INDEX('Raw Data'!$B$5:$F$40,MATCH("Total Assets",'Raw Data'!$A$5:$A$40,0),MATCH(E$4,'Raw Data'!$B$4:$F$4,0))) -> #N/A | F16: =(INDEX('Raw Data'!$B$5:$F$40,MATCH("Revenue",'Raw Data'!$A$5:$A$40,0),MATCH(F$4,'Raw Data'!$B$4:$F$4,0)))/(INDEX('Raw Data'!$B$5:$F$40,MATCH("Total Assets",'Raw Data'!$A$5:$A$40,0),MATCH(F$4,'Raw Data'!$B$4:$F$4,0))) -> #N/A | G16: =(INDEX('Raw Data'!$B$5:$F$40,MATCH("Revenue",'Raw Data'!$A$5:$A$40,0),MATCH(G$4,'Raw Data'!$B$4:$F$4,0)))/(INDEX('Raw Data'!$B$5:$F$40,MATCH("Total Assets",'Raw Data'!$A$5:$A$40,0),MATCH(G$4,'Raw Data'!$B$4:$F$4,0))) -> #N/A | H16: =VLOOKUP($B16,Benchmarks!$A$5:$E$18,2,FALSE()) -> Higher | I16: =VLOOKUP($B16,Benchmarks!$A$5:$E$18,3,FALSE()) -> 1.2 | J16: =IF(H16="Higher",IF(G16>=I16,"Strong",IF(G16>=VLOOKUP($B16,Benchmarks!$A$5:$E$18,4,FALSE()),"Moderate","Weak")),IF(G16<=I16,"Strong",IF(G16<=VLOOKUP($B16,Benchmarks!$A$5:$E$18,4,FALSE()),"Moderate","Weak"))) -> #N/A
A17: Efficiency | B17: Inventory Turnover | C17: =IFERROR((INDEX('Raw Data'!$B$5:$F$40,MATCH("Cost of Goods Sold",'Raw Data'!$A$5:$A$40,0),MATCH(C$4,'Raw Data'!$B$4:$F$4,0)))/(INDEX('Raw Data'!$B$5:$F$40,MATCH("Inventory",'Raw Data'!$A$5:$A$40,0),MATCH(C$4,'Raw Data'!$B$4:$F$4,0))),0) -> 0 | D17: =IFERROR((INDEX('Raw Data'!$B$5:$F$40,MATCH("Cost of Goods Sold",'Raw Data'!$A$5:$A$40,0),MATCH(D$4,'Raw Data'!$B$4:$F$4,0)))/(INDEX('Raw Data'!$B$5:$F$40,MATCH("Inventory",'Raw Data'!$A$5:$A$40,0),MATCH(D$4,'Raw Data'!$B$4:$F$4,0))),0) -> 0 | E17: =IFERROR((INDEX('Raw Data'!$B$5:$F$40,MATCH("Cost of Goods Sold",'Raw Data'!$A$5:$A$40,0),MATCH(E$4,'Raw Data'!$B$4:$F$4,0)))/(INDEX('Raw Data'!$B$5:$F$40,MATCH("Inventory",'Raw Data'!$A$5:$A$40,0),MATCH(E$4,'Raw Data'!$B$4:$F$4,0))),0) -> 0 | F17: =IFERROR((INDEX('Raw Data'!$B$5:$F$40,MATCH("Cost of Goods Sold",'Raw Data'!$A$5:$A$40,0),MATCH(F$4,'Raw Data'!$B$4:$F$4,0)))/(INDEX('Raw Data'!$B$5:$F$40,MATCH("Inventory",'Raw Data'!$A$5:$A$40,0),MATCH(F$4,'Raw Data'!$B$4:$F$4,0))),0) -> 0 | G17: =IFERROR((INDEX('Raw Data'!$B$5:$F$40,MATCH("Cost of Goods Sold",'Raw Data'!$A$5:$A$40,0),MATCH(G$4,'Raw Data'!$B$4:$F$4,0)))/(INDEX('Raw Data'!$B$5:$F$40,MATCH("Inventory",'Raw Data'!$A$5:$A$40,0),MATCH(G$4,'Raw Data'!$B$4:$F$4,0))),0) -> 0 | H17: =VLOOKUP($B17,Benchmarks!$A$5:$E$18,2,FALSE()) -> Higher | I17: =VLOOKUP($B17,Benchmarks!$A$5:$E$18,3,FALSE()) -> 5 | J17: =IF(H17="Higher",IF(G17>=I17,"Strong",IF(G17>=VLOOKUP($B17,Benchmarks!$A$5:$E$18,4,FALSE()),"Moderate","Weak")),IF(G17<=I17,"Strong",IF(G17<=VLOOKUP($B17,Benchmarks!$A$5:$E$18,4,FALSE()),"Moderate","Weak"))) -> Weak
A18: Efficiency | B18: Receivables Turnover | C18: =IFERROR((INDEX('Raw Data'!$B$5:$F$40,MATCH("Revenue",'Raw Data'!$A$5:$A$40,0),MATCH(C$4,'Raw Data'!$B$4:$F$4,0)))/(INDEX('Raw Data'!$B$5:$F$40,MATCH("Accounts Receivable",'Raw Data'!$A$5:$A$40,0),MATCH(C$4,'Raw Data'!$B$4:$F$4,0))),0) -> 0 | D18: =IFERROR((INDEX('Raw Data'!$B$5:$F$40,MATCH("Revenue",'Raw Data'!$A$5:$A$40,0),MATCH(D$4,'Raw Data'!$B$4:$F$4,0)))/(INDEX('Raw Data'!$B$5:$F$40,MATCH("Accounts Receivable",'Raw Data'!$A$5:$A$40,0),MATCH(D$4,'Raw Data'!$B$4:$F$4,0))),0) -> 0 | E18: =IFERROR((INDEX('Raw Data'!$B$5:$F$40,MATCH("Revenue",'Raw Data'!$A$5:$A$40,0),MATCH(E$4,'Raw Data'!$B$4:$F$4,0)))/(INDEX('Raw Data'!$B$5:$F$40,MATCH("Accounts Receivable",'Raw Data'!$A$5:$A$40,0),MATCH(E$4,'Raw Data'!$B$4:$F$4,0))),0) -> 0 | F18: =IFERROR((INDEX('Raw Data'!$B$5:$F$40,MATCH("Revenue",'Raw Data'!$A$5:$A$40,0),MATCH(F$4,'Raw Data'!$B$4:$F$4,0)))/(INDEX('Raw Data'!$B$5:$F$40,MATCH("Accounts Receivable",'Raw Data'!$A$5:$A$40,0),MATCH(F$4,'Raw Data'!$B$4:$F$4,0))),0) -> 0 | G18: =IFERROR((INDEX('Raw Data'!$B$5:$F$40,MATCH("Revenue",'Raw Data'!$A$5:$A$40,0),MATCH(G$4,'Raw Data'!$B$4:$F$4,0)))/(INDEX('Raw Data'!$B$5:$F$40,MATCH("Accounts Receivable",'Raw Data'!$A$5:$A$40,0),MATCH(G$4,'Raw Data'!$B$4:$F$4,0))),0) -> 0 | H18: =VLOOKUP($B18,Benchmarks!$A$5:$E$18,2,FALSE()) -> Higher | I18: =VLOOKUP($B18,Benchmarks!$A$5:$E$18,3,FALSE()) -> 9 | J18: =IF(H18="Higher",IF(G18>=I18,"Strong",IF(G18>=VLOOKUP($B18,Benchmarks!$A$5:$E$18,4,FALSE()),"Moderate","Weak")),IF(G18<=I18,"Strong",IF(G18<=VLOOKUP($B18,Benchmarks!$A$5:$E$18,4,FALSE()),"Moderate","Weak"))) -> Weak

Sheet Raw Data
A1: Meridian Retail Group — Raw Financial Statements, FY2020–FY2024
A2: All figures in USD thousands ($000s), fiscal year ended Dec 31. Blue = input cell. Source: company-prepared financial statements (illustrative dataset).
A4: Line Item | B4: 2020 | C4: 2021 | D4: 2022 | E4: 2023 | F4: 2024
A5: INCOME STATEMENT
A6: Revenue | B6: 120000 | C6: 138000 | D6: 152000 | E6: 171000 | F6: 196000
A7: Cost of Goods Sold | B7: 72000 | C7: 81420 | D7: 89680 | E7: 99180 | F7: 112420
A8: Gross Profit | B8: =B6-B7 -> 48000 | C8: =C6-C7 -> 56580 | D8: =D6-D7 -> 62320 | E8: =E6-E7 -> 71820 | F8: =F6-F7 -> 83580
A9: Operating Expenses (SG&A) | B9: 30000 | C9: 33000 | D9: 35500 | E9: 38500 | F9: 42000
A10: Operating Income (EBIT) | B10: =B8-B9 -> 18000 | C10: =C8-C9 -> 23580 | D10: =D8-D9 -> 26820 | E10: =E8-E9 -> 33320 | F10: =F8-F9 -> 41580
A11: Interest Expense | B11: 3200 | C11: 3000 | D11: 2800 | E11: 2500 | F11: 2200
A12: Earnings Before Tax (EBT) | B12: =B10-B11 -> 14800 | C12: =C10-C11 -> 20580 | D12: =D10-D11 -> 24020 | E12: =E10-E11 -> 30820 | F12: =F10-F11 -> 39380
A13: Tax Rate | B13: 0.25 | C13: 0.25 | D13: 0.25 | E13: 0.25 | F13: 0.25
A14: Tax Expense | B14: =B12*B13 -> 3700 | C14: =C12*C13 -> 5145 | D14: =D12*D13 -> 6005 | E14: =E12*E13 -> 7705 | F14: =F12*F13 -> 9845
A15: Net Income | B15: =B12-B14 -> 11100 | C15: =C12-C14 -> 15435 | D15: =D12-D14 -> 18015 | E15: =E12-E14 -> 23115 | F15: =F12-F14 -> 29535
A17: BALANCE SHEET — ASSETS
A18: Cash & Equivalents | B18: 8000 | C18: 9500 | D18: 11200 | E18: 14500 | F18: 18700
A19: Accounts Receivable | B19: 12000 | C19: 13500 | D19: 14800 | E19: 16200 | F19: 18100
A20: Inventory | B20: 15000 | C20: 16800 | D20: 17900 | E20: 19200 | F20: 20500
A21: Other Current Assets | B21: 2000 | C21: 2200 | D21: 2400 | E21: 2600 | F21: 2800
A22: Total Current Assets | B22: =SUM(B18:B21) -> 37000 | C22: =SUM(C18:C21) -> 42000 | D22: =SUM(D18:D21) -> 46300 | E22: =SUM(E18:E21) -> 52500 | F22: =SUM(F18:F21) -> 60100
A23: Property, Plant & Equipment (net) | B23: 45000 | C23: 47000 | D23: 49500 | E23: 52000 | F23: 55500
A24: Other Long-Term Assets | B24: 5000 | C24: 5200 | D24: 5400 | E24: 5600 | F24: 5800
A25: Total Assets | B25: =B22+B23+B24 -> 87000 | C25: =C22+C23+C24 -> 94200 | D25: =D22+D23+D24 -> 101200 | E25: =E22+E23+E24 -> 110100 | F25: =F22+F23+F24 -> 121400
A27: BALANCE SHEET — LIABILITIES & EQUITY
A28: Accounts Payable | B28: 9000 | C28: 9800 | D28: 10500 | E28: 11200 | F28: 12000
A29: Short-Term Debt | B29: 4000 | C29: 3500 | D29: 3000 | E29: 2500 | F29: 2000
A30: Other Current Liabilities | B30: 3000 | C30: 3200 | D30: 3400 | E30: 3600 | F30: 3800
A31: Total Current Liabilities | B31: =SUM(B28:B30) -> 16000 | C31: =SUM(C28:C30) -> 16500 | D31: =SUM(D28:D30) -> 16900 | E31: =SUM(E28:E30) -> 17300 | F31: =SUM(F28:F30) -> 17800
A32: Long-Term Debt | B32: 25000 | C32: 23000 | D32: 20500 | E32: 18000 | F32: 15500
A33: Other Long-Term Liabilities | B33: 2000 | C33: 2100 | D33: 2200 | E33: 2300 | F33: 2400
A34: Total Liabilities | B34: =B31+B32+B33 -> 43000 | C34: =C31+C32+C33 -> 41600 | D34: =D31+D32+D33 -> 39600 | E34: =E31+E32+E33 -> 37600 | F34: =F31+F32+F33 -> 35700
A35: Total Shareholders' Equity | B35: =B25-B34 -> 44000 | C35: =C25-C34 -> 52600 | D35: =D25-D34 -> 61600 | E35: =E25-E34 -> 72500 | F35: =F25-F34 -> 85700

Sheet Benchmarks
A1: Ratio Benchmark Table
A2: Reference thresholds used by the Ratio Calculations sheet (VLOOKUP) to rate each ratio. Direction indicates whether a higher or lower value is favorable.
A4: Ratio Name | B4: Direction | C4: Strong Threshold | D4: Moderate Threshold | E4: Notes
A5: Current Ratio | B5: Higher | C5: 2 | D5: 1.5 | E5: Current assets vs current liabilities
A6: Quick Ratio | B6: Higher | C6: 1 | D6: 0.75 | E6: Excludes inventory from current assets
A7: Cash Ratio | B7: Higher | C7: 0.5 | D7: 0.25 | E7: Most conservative liquidity measure
A8: Gross Margin | B8: Higher | C8: 0.4 | D8: 0.3 | E8: Gross profit as % of revenue
A9: Operating Margin | B9: Higher | C9: 0.15 | D9: 0.1 | E9: EBIT as % of revenue
A10: Net Profit Margin | B10: Higher | C10: 0.1 | D10: 0.06 | E10: Net income as % of revenue
A11: Return on Assets (ROA) | B11: Higher | C11: 0.08 | D11: 0.05 | E11: Net income vs total assets
A12: Return on Equity (ROE) | B12: Higher | C12: 0.15 | D12: 0.1 | E12: Net income vs shareholders' equity
A13: Debt-to-Equity | B13: Lower | C13: 1 | D13: 1.5 | E13: Total liabilities vs total equity
A14: Debt-to-Assets | B14: Lower | C14: 0.45 | D14: 0.6 | E14: Total liabilities vs total assets
A15: Interest Coverage | B15: Higher | C15: 6 | D15: 3 | E15: EBIT vs interest expense
A16: Asset Turnover | B16: Higher | C16: 1.2 | D16: 0.9 | E16: Revenue generated per dollar of assets
... A18: Receivables Turnover | B18: Higher | C18: 9 | D18: 6 | E18: How efficiently receivables are collected
